tunable_filter/__init__.py
tunable_filter/composite_zoo.py
tunable_filter/py.typed
tunable_filter/tunable.py
tunable_filter-0.0.6.dist-info/LICENSE
tunable_filter-0.0.6.dist-info/METADATA
tunable_filter-0.0.6.dist-info/WHEEL
tunable_filter-0.0.6.dist-info/top_level.txt
tunable_filter-0.0.6.dist-info/RECORD
