Metadata-Version: 2.1
Name: tunable-filter
Version: 0.0.6
Summary: Tunable image filter
Home-page: UNKNOWN
Author: Hirokazu Ishida
Author-email: h-ishida@jsk.imi.i.u-tokyo.ac.jp
License: MIT
Platform: UNKNOWN
License-File: LICENSE
Requires-Dist: numpy
Requires-Dist: opencv-python (>=4.2.0)
Requires-Dist: dataclasses
Requires-Dist: PyYAML
Requires-Dist: types-PyYAML
